fitsrotate/__init__.py
fitsrotate/fitsrotate.py
fitsrotate-0.1.0.dist-info/entry_points.txt
fitsrotate-0.1.0.dist-info/LICENSE
fitsrotate-0.1.0.dist-info/WHEEL
fitsrotate-0.1.0.dist-info/METADATA
fitsrotate-0.1.0.dist-info/RECORD
