Metadata-Version: 2.1
Name: fitsrotate
Version: 0.1.0
Summary: Rotate a FITS file to put spectral axis first
License: MIT
Author: Alec Thomson
Requires-Python: >=3.8,<4.0
Classifier: License :: OSI Approved :: MIT License
Classifier: Programming Language :: Python :: 3
Classifier: Programming Language :: Python :: 3.8
Classifier: Programming Language :: Python :: 3.9
Classifier: Programming Language :: Python :: 3.10
Classifier: Programming Language :: Python :: 3.11
Requires-Dist: astropy (>=5,<6)
Requires-Dist: dask (>=2023,<2024)
Requires-Dist: numpy (>=1.22,<2.0)
